langshark/__init__.py
langshark/client.py
langshark/decorators.py
langshark/utils.py
langshark-0.1.468.dist-info/LICENSE
langshark-0.1.468.dist-info/METADATA
langshark-0.1.468.dist-info/WHEEL
langshark-0.1.468.dist-info/top_level.txt
langshark-0.1.468.dist-info/RECORD
