Metadata-Version: 2.1
Name: langshark
Version: 0.1.468
Summary: A wrapper for Langfuse with enhanced functionality
Home-page: https://github.com/yourusername/langshark
Author: Your Name
Author-email: your.email@example.com
Classifier: Development Status :: 3 - Alpha
Classifier: Intended Audience :: Developers
Classifier: License :: OSI Approved :: MIT License
Classifier: Operating System :: OS Independent
Classifier: Programming Language :: Python :: 3
Classifier: Programming Language :: Python :: 3.7
Classifier: Programming Language :: Python :: 3.8
Classifier: Programming Language :: Python :: 3.9
Requires-Python: >=3.11
License-File: LICENSE
Requires-Dist: langfuse
Requires-Dist: langchain
